cythonsequencefinder/README.MD
cythonsequencefinder/__init__.py
cythonsequencefinder/requirements.txt
cythonsequencefinder/thirdparty.json
cythonsequencefinder-0.10.dist-info/LICENSE.rst
cythonsequencefinder-0.10.dist-info/METADATA
cythonsequencefinder-0.10.dist-info/WHEEL
cythonsequencefinder-0.10.dist-info/top_level.txt
cythonsequencefinder-0.10.dist-info/RECORD
