Metadata-Version: 2.1
Name: cythonsequencefinder
Version: 0.10
Summary: Module for finding sequences in arrays using Cython and NumPy.
Home-page: https://github.com/hansalemaos/cythonsequencefinder
Author: Johannes Fischer
Author-email: aulasparticularesdealemaosp@gmail.com
License: MIT
Keywords: cython,sequences
Classifier: Development Status :: 4 - Beta
Classifier: Programming Language :: Python :: 3 :: Only
Classifier: Programming Language :: Python :: 3.10
Classifier: Topic :: Software Development :: Libraries :: Python Modules
Classifier: Topic :: Utilities
License-File: LICENSE.rst
Requires-Dist: Cython
Requires-Dist: numpy
